Imath.py
OpenEXR.cpython-313-aarch64-linux-musl.so
openexr.libs/libgcc_s-69c45f16.so.1
openexr.libs/libstdc++-1f1a71be.so.6.0.33
openexr-3.4.3.dist-info/METADATA
openexr-3.4.3.dist-info/WHEEL
openexr-3.4.3.dist-info/RECORD
openexr-3.4.3.dist-info/licenses/LICENSE.md
